anvil_ml/__init__.py
anvil_ml/main.py
anvil_ml-0.0.2.dist-info/METADATA
anvil_ml-0.0.2.dist-info/WHEEL
anvil_ml-0.0.2.dist-info/licenses/LICENSE
anvil_ml-0.0.2.dist-info/RECORD
