Metadata-Version: 2.1
Name: anvil_ml
Version: 0.0.2
Summary: Backend service for ForgeML
Project-URL: Homepage, https://github.com/sigil-ml/Forge/tree/main
Project-URL: Bug Tracker, https://github.com/sigil-ml/Forge/tree/main
Author-email: Dalton Walker <dev@daltonwalker.com>
License-File: LICENSE
Classifier: License :: OSI Approved :: MIT License
Classifier: Operating System :: OS Independent
Classifier: Programming Language :: Python :: 3
Requires-Python: >=3.7
